pacevalnet.py
pacevalnet-0.0.2.dist-info/LICENSE
pacevalnet-0.0.2.dist-info/METADATA
pacevalnet-0.0.2.dist-info/WHEEL
pacevalnet-0.0.2.dist-info/top_level.txt
pacevalnet-0.0.2.dist-info/RECORD
