Metadata-Version: 2.1
Name: pacevalnet
Version: 0.0.2
Summary: Test
Author: Dominik Baumann Test
Classifier: Programming Language :: Python :: 3
Classifier: License :: OSI Approved :: MIT License
Classifier: Operating System :: OS Independent
Requires-Python: >=3.6
License-File: LICENSE
Requires-Dist: requests
